{"filename":"D:\\work\\IAMTRADER\\db\\stock\\FUTSTK_MRF_29AUG2019_XX_0.json","collections":[{"name":"5MINUTE","data":[{"OHLC":[{"CLOSE":58900,"HIGH":58950,"LASTTRADETIME":1566813300000,"LOW":58855.05,"OPEN":58887.3,"OPENINTEREST":21000,"QUOTATIONLOT":10,"TRADEDQTY":130},{"CLOSE":58887.3,"HIGH":58947,"LASTTRADETIME":1566813000000,"LOW":58850.2,"OPEN":58888,"OPENINTEREST":20990,"QUOTATIONLOT":10,"TRADEDQTY":230},{"CLOSE":58888,"HIGH":58888,"LASTTRADETIME":1566812700000,"LOW":58690,"OPEN":58704.2,"OPENINTEREST":20680,"QUOTATIONLOT":10,"TRADEDQTY":840},{"CLOSE":58704.2,"HIGH":58719.15,"LASTTRADETIME":1566812400000,"LOW":58563.3,"OPEN":58563.3,"OPENINTEREST":20550,"QUOTATIONLOT":10,"TRADEDQTY":210},{"CLOSE":58563.3,"HIGH":58615.8,"LASTTRADETIME":1566812100000,"LOW":58550,"OPEN":58615.8,"OPENINTEREST":20540,"QUOTATIONLOT":10,"TRADEDQTY":230},{"CLOSE":58615.8,"HIGH":58674.05,"LASTTRADETIME":1566811800000,"LOW":58550,"OPEN":58550,"OPENINTEREST":20540,"QUOTATIONLOT":10,"TRADEDQTY":150},{"CLOSE":58550,"HIGH":58550,"LASTTRADETIME":1566811500000,"LOW":58550,"OPEN":58550,"OPENINTEREST":20520,"QUOTATIONLOT":10,"TRADEDQTY":0},{"CLOSE":58550,"HIGH":58574.95,"LASTTRADETIME":1566811200000,"LOW":58254,"OPEN":58254,"OPENINTEREST":20520,"QUOTATIONLOT":10,"TRADEDQTY":170},{"CLOSE":58254,"HIGH":58349,"LASTTRADETIME":1566810900000,"LOW":58254,"OPEN":58349,"OPENINTEREST":20510,"QUOTATIONLOT":10,"TRADEDQTY":180},{"CLOSE":58349,"HIGH":58410.45,"LASTTRADETIME":1566810600000,"LOW":58320,"OPEN":58410.45,"OPENINTEREST":20530,"QUOTATIONLOT":10,"TRADEDQTY":780},{"CLOSE":58410.45,"HIGH":58410.45,"LASTTRADETIME":1566810300000,"LOW":58400,"OPEN":58400,"OPENINTEREST":20530,"QUOTATIONLOT":10,"TRADEDQTY":30},{"CLOSE":58400,"HIGH":58610.1,"LASTTRADETIME":1566810000000,"LOW":58400,"OPEN":58610.1,"OPENINTEREST":20550,"QUOTATIONLOT":10,"TRADEDQTY":200},{"CLOSE":58610.1,"HIGH":58610.1,"LASTTRADETIME":1566809700000,"LOW":58610.1,"OPEN":58610.1,"OPENINTEREST":20570,"QUOTATIONLOT":10,"TRADEDQTY":200},{"CLOSE":58610.1,"HIGH":58610.1,"LASTTRADETIME":1566809400000,"LOW":58610.1,"OPEN":58610.1,"OPENINTEREST":20580,"QUOTATIONLOT":10,"TRADEDQTY":0},{"CLOSE":58610.1,"HIGH":58760,"LASTTRADETIME":1566809100000,"LOW":58600,"OPEN":58760,"OPENINTEREST":20580,"QUOTATIONLOT":10,"TRADEDQTY":130},{"CLOSE":58760,"HIGH":58760,"LASTTRADETIME":1566808800000,"LOW":58621.25,"OPEN":58679.3,"OPENINTEREST":20620,"QUOTATIONLOT":10,"TRADEDQTY":50},{"CLOSE":58679.3,"HIGH":58779.9,"LASTTRADETIME":1566808500000,"LOW":58621.35,"OPEN":58700,"OPENINTEREST":20650,"QUOTATIONLOT":10,"TRADEDQTY":160},{"CLOSE":58700,"HIGH":58700,"LASTTRADETIME":1566808200000,"LOW":58700,"OPEN":58700,"OPENINTEREST":20670,"QUOTATIONLOT":10,"TRADEDQTY":10},{"CLOSE":58700,"HIGH":58778.45,"LASTTRADETIME":1566807900000,"LOW":58609.7,"OPEN":58650,"OPENINTEREST":20680,"QUOTATIONLOT":10,"TRADEDQTY":80},{"CLOSE":58650,"HIGH":58674.7,"LASTTRADETIME":1566807600000,"LOW":58649.95,"OPEN":58660,"OPENINTEREST":20660,"QUOTATIONLOT":10,"TRADEDQTY":30},{"CLOSE":58660,"HIGH":58660,"LASTTRADETIME":1566807300000,"LOW":58450,"OPEN":58450,"OPENINTEREST":20650,"QUOTATIONLOT":10,"TRADEDQTY":80},{"CLOSE":58450,"HIGH":58525,"LASTTRADETIME":1566807000000,"LOW":58325.55,"OPEN":58325.55,"OPENINTEREST":20670,"QUOTATIONLOT":10,"TRADEDQTY":160},{"CLOSE":58325.55,"HIGH":58417.8,"LASTTRADETIME":1566806700000,"LOW":58325.55,"OPEN":58417.8,"OPENINTEREST":20720,"QUOTATIONLOT":10,"TRADEDQTY":120},{"CLOSE":58417.8,"HIGH":58417.8,"LASTTRADETIME":1566806400000,"LOW":58384.35,"OPEN":58384.35,"OPENINTEREST":20800,"QUOTATIONLOT":10,"TRADEDQTY":20},{"CLOSE":58384.35,"HIGH":58384.35,"LASTTRADETIME":1566806100000,"LOW":58290,"OPEN":58290,"OPENINTEREST":20790,"QUOTATIONLOT":10,"TRADEDQTY":10},{"CLOSE":58290,"HIGH":58350,"LASTTRADETIME":1566805800000,"LOW":58290,"OPEN":58292.3,"OPENINTEREST":20800,"QUOTATIONLOT":10,"TRADEDQTY":40},{"CLOSE":58292.3,"HIGH":58300,"LASTTRADETIME":1566805500000,"LOW":58292.3,"OPEN":58300,"OPENINTEREST":20810,"QUOTATIONLOT":10,"TRADEDQTY":10},{"CLOSE":58300,"HIGH":58300,"LASTTRADETIME":1566805200000,"LOW":58251,"OPEN":58251,"OPENINTEREST":20780,"QUOTATIONLOT":10,"TRADEDQTY":10},{"CLOSE":58251,"HIGH":58251,"LASTTRADETIME":1566804900000,"LOW":58251,"OPEN":58251,"OPENINTEREST":20780,"QUOTATIONLOT":10,"TRADEDQTY":70},{"CLOSE":58251,"HIGH":58251,"LASTTRADETIME":1566804600000,"LOW":58200,"OPEN":58200,"OPENINTEREST":20780,"QUOTATIONLOT":10,"TRADEDQTY":10},{"CLOSE":58200,"HIGH":58200,"LASTTRADETIME":1566804300000,"LOW":58143.9,"OPEN":58179.4,"OPENINTEREST":20790,"QUOTATIONLOT":10,"TRADEDQTY":30},{"CLOSE":58179.4,"HIGH":58190,"LASTTRADETIME":1566804000000,"LOW":58179.4,"OPEN":58190,"OPENINTEREST":20790,"QUOTATIONLOT":10,"TRADEDQTY":10},{"CLOSE":58190,"HIGH":58190,"LASTTRADETIME":1566803700000,"LOW":58027.15,"OPEN":58100,"OPENINTEREST":20780,"QUOTATIONLOT":10,"TRADEDQTY":60},{"CLOSE":58100,"HIGH":58148.15,"LASTTRADETIME":1566803400000,"LOW":58080,"OPEN":58148.15,"OPENINTEREST":20790,"QUOTATIONLOT":10,"TRADEDQTY":110},{"CLOSE":58148.15,"HIGH":58148.15,"LASTTRADETIME":1566803100000,"LOW":58148.15,"OPEN":58148.15,"OPENINTEREST":20760,"QUOTATIONLOT":10,"TRADEDQTY":0},{"CLOSE":58148.15,"HIGH":58148.15,"LASTTRADETIME":1566802800000,"LOW":58000,"OPEN":58000,"OPENINTEREST":20780,"QUOTATIONLOT":10,"TRADEDQTY":180},{"CLOSE":58000,"HIGH":58000,"LASTTRADETIME":1566802500000,"LOW":57956.3,"OPEN":57956.3,"OPENINTEREST":20810,"QUOTATIONLOT":10,"TRADEDQTY":80},{"CLOSE":57956.3,"HIGH":58019.6,"LASTTRADETIME":1566802200000,"LOW":57956.3,"OPEN":58010.3,"OPENINTEREST":20870,"QUOTATIONLOT":10,"TRADEDQTY":220},{"CLOSE":58010.3,"HIGH":58010.3,"LASTTRADETIME":1566801900000,"LOW":57949.9,"OPEN":57949.9,"OPENINTEREST":20860,"QUOTATIONLOT":10,"TRADEDQTY":170},{"CLOSE":57949.9,"HIGH":57949.9,"LASTTRADETIME":1566801600000,"LOW":57949.9,"OPEN":57949.9,"OPENINTEREST":20850,"QUOTATIONLOT":10,"TRADEDQTY":10},{"CLOSE":57949.95,"HIGH":58000,"LASTTRADETIME":1566801300000,"LOW":57949.95,"OPEN":58000,"OPENINTEREST":20840,"QUOTATIONLOT":10,"TRADEDQTY":10},{"CLOSE":58000,"HIGH":58000,"LASTTRADETIME":1566801000000,"LOW":58000,"OPEN":58000,"OPENINTEREST":20920,"QUOTATIONLOT":10,"TRADEDQTY":0},{"CLOSE":58000,"HIGH":58000,"LASTTRADETIME":1566800700000,"LOW":58000,"OPEN":58000,"OPENINTEREST":20920,"QUOTATIONLOT":10,"TRADEDQTY":0},{"CLOSE":58000,"HIGH":58000,"LASTTRADETIME":1566800400000,"LOW":58000,"OPEN":58000,"OPENINTEREST":20920,"QUOTATIONLOT":10,"TRADEDQTY":0},{"CLOSE":58000,"HIGH":58000,"LASTTRADETIME":1566800100000,"LOW":58000,"OPEN":58000,"OPENINTEREST":20920,"QUOTATIONLOT":10,"TRADEDQTY":100},{"CLOSE":58000,"HIGH":58040,"LASTTRADETIME":1566799800000,"LOW":57969.65,"OPEN":57969.65,"OPENINTEREST":20940,"QUOTATIONLOT":10,"TRADEDQTY":140},{"CLOSE":57969.65,"HIGH":57969.65,"LASTTRADETIME":1566799500000,"LOW":57947.2,"OPEN":57947.2,"OPENINTEREST":20920,"QUOTATIONLOT":10,"TRADEDQTY":30},{"CLOSE":57947.2,"HIGH":58010,"LASTTRADETIME":1566799200000,"LOW":57947.2,"OPEN":58010,"OPENINTEREST":20920,"QUOTATIONLOT":10,"TRADEDQTY":30},{"CLOSE":58010,"HIGH":58010,"LASTTRADETIME":1566798900000,"LOW":57977,"OPEN":57977,"OPENINTEREST":20940,"QUOTATIONLOT":10,"TRADEDQTY":60},{"CLOSE":57977,"HIGH":57977,"LASTTRADETIME":1566798600000,"LOW":57900,"OPEN":57900,"OPENINTEREST":20960,"QUOTATIONLOT":10,"TRADEDQTY":30},{"CLOSE":57914.9,"HIGH":57914.9,"LASTTRADETIME":1566798300000,"LOW":57914.9,"OPEN":57914.9,"OPENINTEREST":20970,"QUOTATIONLOT":10,"TRADEDQTY":10},{"CLOSE":57914.9,"HIGH":57966.5,"LASTTRADETIME":1566798000000,"LOW":57899.7,"OPEN":57966.5,"OPENINTEREST":20970,"QUOTATIONLOT":10,"TRADEDQTY":20},{"CLOSE":57966.5,"HIGH":57966.5,"LASTTRADETIME":1566797700000,"LOW":57966.5,"OPEN":57966.5,"OPENINTEREST":20980,"QUOTATIONLOT":10,"TRADEDQTY":0},{"CLOSE":57966.5,"HIGH":57966.5,"LASTTRADETIME":1566797400000,"LOW":57805.55,"OPEN":57865.85,"OPENINTEREST":20980,"QUOTATIONLOT":10,"TRADEDQTY":60},{"CLOSE":57865.85,"HIGH":57865.85,"LASTTRADETIME":1566797100000,"LOW":57865.85,"OPEN":57865.85,"OPENINTEREST":21010,"QUOTATIONLOT":10,"TRADEDQTY":0},{"CLOSE":57865.85,"HIGH":57865.85,"LASTTRADETIME":1566796800000,"LOW":57865.85,"OPEN":57865.85,"OPENINTEREST":21010,"QUOTATIONLOT":10,"TRADEDQTY":0},{"CLOSE":57865.85,"HIGH":57888.2,"LASTTRADETIME":1566796500000,"LOW":57865.85,"OPEN":57888.2,"OPENINTEREST":21010,"QUOTATIONLOT":10,"TRADEDQTY":10},{"CLOSE":57888.2,"HIGH":57888.2,"LASTTRADETIME":1566796200000,"LOW":57888.2,"OPEN":57888.2,"OPENINTEREST":21020,"QUOTATIONLOT":10,"TRADEDQTY":0},{"CLOSE":57888.2,"HIGH":57888.2,"LASTTRADETIME":1566795900000,"LOW":57748.8,"OPEN":57748.8,"OPENINTEREST":21020,"QUOTATIONLOT":10,"TRADEDQTY":60},{"CLOSE":57748.8,"HIGH":57900,"LASTTRADETIME":1566795600000,"LOW":57748.8,"OPEN":57784.55,"OPENINTEREST":20980,"QUOTATIONLOT":10,"TRADEDQTY":170},{"CLOSE":57784.55,"HIGH":57895.9,"LASTTRADETIME":1566795300000,"LOW":57587.6,"OPEN":57700,"OPENINTEREST":20960,"QUOTATIONLOT":10,"TRADEDQTY":130},{"CLOSE":57700,"HIGH":57700,"LASTTRADETIME":1566795000000,"LOW":57509.3,"OPEN":57509.3,"OPENINTEREST":20960,"QUOTATIONLOT":10,"TRADEDQTY":230},{"CLOSE":57509.3,"HIGH":57509.3,"LASTTRADETIME":1566794700000,"LOW":57356.15,"OPEN":57356.15,"OPENINTEREST":20900,"QUOTATIONLOT":10,"TRADEDQTY":70},{"CLOSE":57356.15,"HIGH":57356.15,"LASTTRADETIME":1566794400000,"LOW":57208.5,"OPEN":57265,"OPENINTEREST":20910,"QUOTATIONLOT":10,"TRADEDQTY":40},{"CLOSE":57310.1,"HIGH":57310.1,"LASTTRADETIME":1566794100000,"LOW":57302.15,"OPEN":57302.15,"OPENINTEREST":20900,"QUOTATIONLOT":10,"TRADEDQTY":10},{"CLOSE":57302.15,"HIGH":57524.2,"LASTTRADETIME":1566793800000,"LOW":57264.4,"OPEN":57524.2,"OPENINTEREST":20910,"QUOTATIONLOT":10,"TRADEDQTY":70},{"CLOSE":57524.2,"HIGH":57580.1,"LASTTRADETIME":1566793500000,"LOW":57524.2,"OPEN":57580.1,"OPENINTEREST":20930,"QUOTATIONLOT":10,"TRADEDQTY":30},{"CLOSE":57580.1,"HIGH":57580.1,"LASTTRADETIME":1566793200000,"LOW":57454.8,"OPEN":57454.8,"OPENINTEREST":20960,"QUOTATIONLOT":10,"TRADEDQTY":10},{"CLOSE":57454.8,"HIGH":57520,"LASTTRADETIME":1566792900000,"LOW":57351,"OPEN":57451,"OPENINTEREST":20980,"QUOTATIONLOT":10,"TRADEDQTY":200},{"CLOSE":57520,"HIGH":57700,"LASTTRADETIME":1566792600000,"LOW":57483.85,"OPEN":57700,"OPENINTEREST":20980,"QUOTATIONLOT":10,"TRADEDQTY":170},{"CLOSE":57661.35,"HIGH":57661.35,"LASTTRADETIME":1566792300000,"LOW":57500,"OPEN":57523.4,"OPENINTEREST":20420,"QUOTATIONLOT":10,"TRADEDQTY":720},{"CLOSE":57523.4,"HIGH":58128.25,"LASTTRADETIME":1566792000000,"LOW":57475.7,"OPEN":58128.25,"OPENINTEREST":20500,"QUOTATIONLOT":10,"TRADEDQTY":350},{"CLOSE":58128.25,"HIGH":58198.5,"LASTTRADETIME":1566791700000,"LOW":58050,"OPEN":58050,"OPENINTEREST":20480,"QUOTATIONLOT":10,"TRADEDQTY":80},{"CLOSE":58050,"HIGH":58200.2,"LASTTRADETIME":1566791400000,"LOW":57920.65,"OPEN":58013.3,"OPENINTEREST":20490,"QUOTATIONLOT":10,"TRADEDQTY":110},{"CLOSE":58013.3,"HIGH":58465.7,"LASTTRADETIME":1566791100000,"LOW":57988.35,"OPEN":58465.7,"OPENINTEREST":20480,"QUOTATIONLOT":10,"TRADEDQTY":50},{"CLOSE":57906,"HIGH":57906,"LASTTRADETIME":1566554400000,"LOW":57906,"OPEN":57906,"OPENINTEREST":22560,"QUOTATIONLOT":10,"TRADEDQTY":0},{"CLOSE":57906,"HIGH":58099.95,"LASTTRADETIME":1566554100000,"LOW":57900.05,"OPEN":58099.95,"OPENINTEREST":22630,"QUOTATIONLOT":10,"TRADEDQTY":200},{"CLOSE":58099.95,"HIGH":58216.35,"LASTTRADETIME":1566553800000,"LOW":58015.65,"OPEN":58216.35,"OPENINTEREST":22660,"QUOTATIONLOT":10,"TRADEDQTY":170},{"CLOSE":58216.35,"HIGH":58216.35,"LASTTRADETIME":1566553500000,"LOW":57902.25,"OPEN":57950.05,"OPENINTEREST":22770,"QUOTATIONLOT":10,"TRADEDQTY":330},{"CLOSE":57950.05,"HIGH":57996.55,"LASTTRADETIME":1566553200000,"LOW":57900,"OPEN":57950,"OPENINTEREST":22730,"QUOTATIONLOT":10,"TRADEDQTY":130},{"CLOSE":57950,"HIGH":57950,"LASTTRADETIME":1566552900000,"LOW":57780.3,"OPEN":57780.3,"OPENINTEREST":22780,"QUOTATIONLOT":10,"TRADEDQTY":290},{"CLOSE":57780.3,"HIGH":57800,"LASTTRADETIME":1566552600000,"LOW":57695,"OPEN":57724.95,"OPENINTEREST":22920,"QUOTATIONLOT":10,"TRADEDQTY":150},{"CLOSE":57724.95,"HIGH":57970.95,"LASTTRADETIME":1566552300000,"LOW":57650,"OPEN":57970.95,"OPENINTEREST":22940,"QUOTATIONLOT":10,"TRADEDQTY":320},{"CLOSE":57970.95,"HIGH":58050,"LASTTRADETIME":1566552000000,"LOW":57970.9,"OPEN":58050,"OPENINTEREST":22840,"QUOTATIONLOT":10,"TRADEDQTY":50},{"CLOSE":58050,"HIGH":58054.45,"LASTTRADETIME":1566551700000,"LOW":57989.5,"OPEN":57989.5,"OPENINTEREST":22850,"QUOTATIONLOT":10,"TRADEDQTY":60},{"CLOSE":57989.5,"HIGH":58201,"LASTTRADETIME":1566551400000,"LOW":57956,"OPEN":58201,"OPENINTEREST":22840,"QUOTATIONLOT":10,"TRADEDQTY":230},{"CLOSE":58201,"HIGH":58546.5,"LASTTRADETIME":1566551100000,"LOW":58124.35,"OPEN":58200,"OPENINTEREST":22820,"QUOTATIONLOT":10,"TRADEDQTY":1330},{"CLOSE":58200,"HIGH":58278.05,"LASTTRADETIME":1566550800000,"LOW":58200,"OPEN":58210.7,"OPENINTEREST":22740,"QUOTATIONLOT":10,"TRADEDQTY":150},{"CLOSE":58210.7,"HIGH":58210.95,"LASTTRADETIME":1566550500000,"LOW":58033.55,"OPEN":58033.55,"OPENINTEREST":22670,"QUOTATIONLOT":10,"TRADEDQTY":130},{"CLOSE":58164.95,"HIGH":58165.15,"LASTTRADETIME":1566550200000,"LOW":58164.95,"OPEN":58165.15,"OPENINTEREST":22670,"QUOTATIONLOT":10,"TRADEDQTY":20},{"CLOSE":58165.15,"HIGH":58243.35,"LASTTRADETIME":1566549900000,"LOW":58165.15,"OPEN":58165.2,"OPENINTEREST":22670,"QUOTATIONLOT":10,"TRADEDQTY":40},{"CLOSE":58165.2,"HIGH":58304.75,"LASTTRADETIME":1566549600000,"LOW":58150,"OPEN":58304.75,"OPENINTEREST":22660,"QUOTATIONLOT":10,"TRADEDQTY":60},{"CLOSE":58304.75,"HIGH":58313,"LASTTRADETIME":1566549300000,"LOW":58226.5,"OPEN":58226.5,"OPENINTEREST":22680,"QUOTATIONLOT":10,"TRADEDQTY":250},{"CLOSE":58226.5,"HIGH":58226.5,"LASTTRADETIME":1566549000000,"LOW":58106.6,"OPEN":58106.6,"OPENINTEREST":22690,"QUOTATIONLOT":10,"TRADEDQTY":40},{"CLOSE":58106.6,"HIGH":58226.5,"LASTTRADETIME":1566548700000,"LOW":58106.6,"OPEN":58226.5,"OPENINTEREST":22690,"QUOTATIONLOT":10,"TRADEDQTY":40},{"CLOSE":58226.5,"HIGH":58226.5,"LASTTRADETIME":1566548400000,"LOW":58176,"OPEN":58176,"OPENINTEREST":22770,"QUOTATIONLOT":10,"TRADEDQTY":320},{"CLOSE":58176,"HIGH":58176,"LASTTRADETIME":1566548100000,"LOW":58176,"OPEN":58176,"OPENINTEREST":22840,"QUOTATIONLOT":10,"TRADEDQTY":0},{"CLOSE":58176,"HIGH":58217.95,"LASTTRADETIME":1566547800000,"LOW":58049.75,"OPEN":58149.95,"OPENINTEREST":22840,"QUOTATIONLOT":10,"TRADEDQTY":90},{"CLOSE":58149.95,"HIGH":58149.95,"LASTTRADETIME":1566547500000,"LOW":58086.9,"OPEN":58086.9,"OPENINTEREST":22830,"QUOTATIONLOT":10,"TRADEDQTY":120},{"CLOSE":58110,"HIGH":58292.65,"LASTTRADETIME":1566547200000,"LOW":58110,"OPEN":58292.65,"OPENINTEREST":22880,"QUOTATIONLOT":10,"TRADEDQTY":80},{"CLOSE":58292.65,"HIGH":58292.65,"LASTTRADETIME":1566546900000,"LOW":58292.65,"OPEN":58292.65,"OPENINTEREST":22850,"QUOTATIONLOT":10,"TRADEDQTY":0},{"CLOSE":58292.65,"HIGH":58293.95,"LASTTRADETIME":1566546600000,"LOW":58194.8,"OPEN":58194.8,"OPENINTEREST":22850,"QUOTATIONLOT":10,"TRADEDQTY":40},{"CLOSE":58194.8,"HIGH":58294.05,"LASTTRADETIME":1566546300000,"LOW":58120.45,"OPEN":58220,"OPENINTEREST":22850,"QUOTATIONLOT":10,"TRADEDQTY":170},{"CLOSE":58217.2,"HIGH":58220,"LASTTRADETIME":1566546000000,"LOW":58065,"OPEN":58065,"OPENINTEREST":22820,"QUOTATIONLOT":10,"TRADEDQTY":140},{"CLOSE":58065,"HIGH":58065,"LASTTRADETIME":1566545700000,"LOW":57912.15,"OPEN":57912.15,"OPENINTEREST":22810,"QUOTATIONLOT":10,"TRADEDQTY":40},{"CLOSE":57912.15,"HIGH":58069.6,"LASTTRADETIME":1566545400000,"LOW":57910.55,"OPEN":58069.6,"OPENINTEREST":22810,"QUOTATIONLOT":10,"TRADEDQTY":40},{"CLOSE":58069.6,"HIGH":58069.6,"LASTTRADETIME":1566545100000,"LOW":57960,"OPEN":57960,"OPENINTEREST":22810,"QUOTATIONLOT":10,"TRADEDQTY":50},{"CLOSE":57960,"HIGH":58068.75,"LASTTRADETIME":1566544800000,"LOW":57923.5,"OPEN":57923.5,"OPENINTEREST":22810,"QUOTATIONLOT":10,"TRADEDQTY":70},{"CLOSE":57923.5,"HIGH":58068.7,"LASTTRADETIME":1566544500000,"LOW":57923.5,"OPEN":58000.05,"OPENINTEREST":22770,"QUOTATIONLOT":10,"TRADEDQTY":50},{"CLOSE":58000.05,"HIGH":58060,"LASTTRADETIME":1566544200000,"LOW":57974.5,"OPEN":57974.5,"OPENINTEREST":22780,"QUOTATIONLOT":10,"TRADEDQTY":140},{"CLOSE":57895,"HIGH":57974.5,"LASTTRADETIME":1566543900000,"LOW":57842.45,"OPEN":57842.45,"OPENINTEREST":22710,"QUOTATIONLOT":10,"TRADEDQTY":90},{"CLOSE":57842.45,"HIGH":57842.45,"LASTTRADETIME":1566543600000,"LOW":57797,"OPEN":57797,"OPENINTEREST":22660,"QUOTATIONLOT":10,"TRADEDQTY":40},{"CLOSE":57702.75,"HIGH":57794.6,"LASTTRADETIME":1566543300000,"LOW":57700,"OPEN":57794.6,"OPENINTEREST":22660,"QUOTATIONLOT":10,"TRADEDQTY":80},{"CLOSE":57794.6,"HIGH":57797,"LASTTRADETIME":1566543000000,"LOW":57683.45,"OPEN":57683.45,"OPENINTEREST":22660,"QUOTATIONLOT":10,"TRADEDQTY":40},{"CLOSE":57683.45,"HIGH":57683.45,"LASTTRADETIME":1566542700000,"LOW":57683.45,"OPEN":57683.45,"OPENINTEREST":22650,"QUOTATIONLOT":10,"TRADEDQTY":0},{"CLOSE":57683.45,"HIGH":57790,"LASTTRADETIME":1566542400000,"LOW":57683.45,"OPEN":57790,"OPENINTEREST":22650,"QUOTATIONLOT":10,"TRADEDQTY":50},{"CLOSE":57790,"HIGH":57790,"LASTTRADETIME":1566542100000,"LOW":57603.45,"OPEN":57603.45,"OPENINTEREST":22570,"QUOTATIONLOT":10,"TRADEDQTY":90},{"CLOSE":57603.45,"HIGH":57603.45,"LASTTRADETIME":1566541800000,"LOW":57603.45,"OPEN":57603.45,"OPENINTEREST":22580,"QUOTATIONLOT":10,"TRADEDQTY":10},{"CLOSE":57603.45,"HIGH":57603.5,"LASTTRADETIME":1566541500000,"LOW":57535.1,"OPEN":57535.15,"OPENINTEREST":22580,"QUOTATIONLOT":10,"TRADEDQTY":40},{"CLOSE":57535.15,"HIGH":57601,"LASTTRADETIME":1566541200000,"LOW":57501.25,"OPEN":57501.25,"OPENINTEREST":22550,"QUOTATIONLOT":10,"TRADEDQTY":30},{"CLOSE":57501.25,"HIGH":57501.25,"LASTTRADETIME":1566540900000,"LOW":57501.25,"OPEN":57501.25,"OPENINTEREST":22530,"QUOTATIONLOT":10,"TRADEDQTY":0},{"CLOSE":57501.25,"HIGH":57501.25,"LASTTRADETIME":1566540600000,"LOW":57501.15,"OPEN":57501.15,"OPENINTEREST":22530,"QUOTATIONLOT":10,"TRADEDQTY":20},{"CLOSE":57501.15,"HIGH":57501.15,"LASTTRADETIME":1566540300000,"LOW":57501.15,"OPEN":57501.15,"OPENINTEREST":22530,"QUOTATIONLOT":10,"TRADEDQTY":0},{"CLOSE":57501.15,"HIGH":57501.15,"LASTTRADETIME":1566540000000,"LOW":57501.05,"OPEN":57501.05,"OPENINTEREST":22530,"QUOTATIONLOT":10,"TRADEDQTY":20},{"CLOSE":57501.05,"HIGH":57501.05,"LASTTRADETIME":1566539700000,"LOW":57400,"OPEN":57400,"OPENINTEREST":22540,"QUOTATIONLOT":10,"TRADEDQTY":20},{"CLOSE":57400,"HIGH":57400,"LASTTRADETIME":1566539400000,"LOW":57400,"OPEN":57400,"OPENINTEREST":22520,"QUOTATIONLOT":10,"TRADEDQTY":40},{"CLOSE":57400,"HIGH":57490.75,"LASTTRADETIME":1566539100000,"LOW":57384.65,"OPEN":57433.7,"OPENINTEREST":22510,"QUOTATIONLOT":10,"TRADEDQTY":60},{"CLOSE":57433.7,"HIGH":57433.7,"LASTTRADETIME":1566538800000,"LOW":57344.3,"OPEN":57389.15,"OPENINTEREST":22470,"QUOTATIONLOT":10,"TRADEDQTY":30},{"CLOSE":57389.15,"HIGH":57604.25,"LASTTRADETIME":1566538500000,"LOW":57389.15,"OPEN":57500,"OPENINTEREST":22410,"QUOTATIONLOT":10,"TRADEDQTY":220},{"CLOSE":57695,"HIGH":57797,"LASTTRADETIME":1566538200000,"LOW":57637.85,"OPEN":57750,"OPENINTEREST":22310,"QUOTATIONLOT":10,"TRADEDQTY":320},{"CLOSE":57720,"HIGH":57720,"LASTTRADETIME":1566537900000,"LOW":57603.05,"OPEN":57610.05,"OPENINTEREST":22300,"QUOTATIONLOT":10,"TRADEDQTY":150},{"CLOSE":57610.05,"HIGH":57690,"LASTTRADETIME":1566537600000,"LOW":57600.3,"OPEN":57690,"OPENINTEREST":22250,"QUOTATIONLOT":10,"TRADEDQTY":90},{"CLOSE":57690,"HIGH":57737.15,"LASTTRADETIME":1566537300000,"LOW":57610,"OPEN":57737.15,"OPENINTEREST":22260,"QUOTATIONLOT":10,"TRADEDQTY":80},{"CLOSE":57737.15,"HIGH":57745.05,"LASTTRADETIME":1566537000000,"LOW":57666.85,"OPEN":57692.7,"OPENINTEREST":22280,"QUOTATIONLOT":10,"TRADEDQTY":110},{"CLOSE":57692.7,"HIGH":57692.7,"LASTTRADETIME":1566536700000,"LOW":57267.7,"OPEN":57300,"OPENINTEREST":22270,"QUOTATIONLOT":10,"TRADEDQTY":150},{"CLOSE":57300,"HIGH":57331.1,"LASTTRADETIME":1566536400000,"LOW":57267,"OPEN":57331.1,"OPENINTEREST":22240,"QUOTATIONLOT":10,"TRADEDQTY":110},{"CLOSE":57330.05,"HIGH":57330.05,"LASTTRADETIME":1566536100000,"LOW":57120,"OPEN":57120,"OPENINTEREST":22190,"QUOTATIONLOT":10,"TRADEDQTY":60},{"CLOSE":57120,"HIGH":57172.15,"LASTTRADETIME":1566535800000,"LOW":57000.5,"OPEN":57052.9,"OPENINTEREST":22190,"QUOTATIONLOT":10,"TRADEDQTY":130},{"CLOSE":57052.9,"HIGH":57169.5,"LASTTRADETIME":1566535500000,"LOW":57052.9,"OPEN":57169.5,"OPENINTEREST":22140,"QUOTATIONLOT":10,"TRADEDQTY":50},{"CLOSE":57172.45,"HIGH":57172.45,"LASTTRADETIME":1566535200000,"LOW":57050,"OPEN":57050,"OPENINTEREST":22130,"QUOTATIONLOT":10,"TRADEDQTY":10},{"CLOSE":57050,"HIGH":57172.65,"LASTTRADETIME":1566534900000,"LOW":57000,"OPEN":57172.65,"OPENINTEREST":22060,"QUOTATIONLOT":10,"TRADEDQTY":130},{"CLOSE":57172.65,"HIGH":57172.65,"LASTTRADETIME":1566534600000,"LOW":56999.05,"OPEN":57000,"OPENINTEREST":22040,"QUOTATIONLOT":10,"TRADEDQTY":120},{"CLOSE":57000,"HIGH":57094.25,"LASTTRADETIME":1566534300000,"LOW":56974,"OPEN":57000,"OPENINTEREST":21780,"QUOTATIONLOT":10,"TRADEDQTY":430},{"CLOSE":57000,"HIGH":57000,"LASTTRADETIME":1566534000000,"LOW":56637.35,"OPEN":56637.35,"OPENINTEREST":21680,"QUOTATIONLOT":10,"TRADEDQTY":150},{"CLOSE":56637.35,"HIGH":56637.35,"LASTTRADETIME":1566533700000,"LOW":56456.9,"OPEN":56475,"OPENINTEREST":21690,"QUOTATIONLOT":10,"TRADEDQTY":190},{"CLOSE":56475,"HIGH":56650,"LASTTRADETIME":1566533400000,"LOW":56373.55,"OPEN":56650,"OPENINTEREST":21620,"QUOTATIONLOT":10,"TRADEDQTY":490},{"CLOSE":56650,"HIGH":56825,"LASTTRADETIME":1566533100000,"LOW":56650,"OPEN":56825,"OPENINTEREST":21680,"QUOTATIONLOT":10,"TRADEDQTY":350},{"CLOSE":56825,"HIGH":57133.8,"LASTTRADETIME":1566532800000,"LOW":56686.3,"OPEN":57117.95,"OPENINTEREST":21480,"QUOTATIONLOT":10,"TRADEDQTY":600},{"CLOSE":57117.95,"HIGH":57280.7,"LASTTRADETIME":1566532500000,"LOW":57116,"OPEN":57280.7,"OPENINTEREST":21360,"QUOTATIONLOT":10,"TRADEDQTY":50},{"CLOSE":57280.7,"HIGH":57300,"LASTTRADETIME":1566532200000,"LOW":57155,"OPEN":57155,"OPENINTEREST":21130,"QUOTATIONLOT":10,"TRADEDQTY":350},{"CLOSE":57155,"HIGH":57329.4,"LASTTRADETIME":1566531900000,"LOW":57014,"OPEN":57329.4,"OPENINTEREST":21140,"QUOTATIONLOT":10,"TRADEDQTY":160},{"CLOSE":57200,"HIGH":57304.85,"LASTTRADETIME":1566467700000,"LOW":57200,"OPEN":57267.9,"OPENINTEREST":22950,"QUOTATIONLOT":10,"TRADEDQTY":540},{"CLOSE":57267.9,"HIGH":57412.75,"LASTTRADETIME":1566467400000,"LOW":57211.1,"OPEN":57367.55,"OPENINTEREST":23070,"QUOTATIONLOT":10,"TRADEDQTY":900},{"CLOSE":57367.55,"HIGH":57424.85,"LASTTRADETIME":1566467100000,"LOW":57349.95,"OPEN":57400,"OPENINTEREST":23050,"QUOTATIONLOT":10,"TRADEDQTY":270},{"CLOSE":57400,"HIGH":57440.9,"LASTTRADETIME":1566466800000,"LOW":57394.05,"OPEN":57421.05,"OPENINTEREST":23050,"QUOTATIONLOT":10,"TRADEDQTY":420},{"CLOSE":57421.05,"HIGH":57470.2,"LASTTRADETIME":1566466500000,"LOW":57374.7,"OPEN":57374.7,"OPENINTEREST":23000,"QUOTATIONLOT":10,"TRADEDQTY":120},{"CLOSE":57374.7,"HIGH":57494.95,"LASTTRADETIME":1566466200000,"LOW":57360.75,"OPEN":57494.95,"OPENINTEREST":22910,"QUOTATIONLOT":10,"TRADEDQTY":500},{"CLOSE":57494.95,"HIGH":57494.95,"LASTTRADETIME":1566465900000,"LOW":57324.3,"OPEN":57324.3,"OPENINTEREST":22980,"QUOTATIONLOT":10,"TRADEDQTY":110},{"CLOSE":57324.3,"HIGH":57510.3,"LASTTRADETIME":1566465600000,"LOW":57324.3,"OPEN":57483.55,"OPENINTEREST":23030,"QUOTATIONLOT":10,"TRADEDQTY":310},{"CLOSE":57525,"HIGH":57530.05,"LASTTRADETIME":1566465300000,"LOW":57463.2,"OPEN":57463.2,"OPENINTEREST":23020,"QUOTATIONLOT":10,"TRADEDQTY":90},{"CLOSE":57463.2,"HIGH":57463.2,"LASTTRADETIME":1566465000000,"LOW":57400,"OPEN":57400,"OPENINTEREST":23000,"QUOTATIONLOT":10,"TRADEDQTY":130},{"CLOSE":57400,"HIGH":57500.1,"LASTTRADETIME":1566464700000,"LOW":57365.2,"OPEN":57500.1,"OPENINTEREST":22990,"QUOTATIONLOT":10,"TRADEDQTY":400},{"CLOSE":57500.1,"HIGH":57500.1,"LASTTRADETIME":1566464400000,"LOW":57500,"OPEN":57500,"OPENINTEREST":22820,"QUOTATIONLOT":10,"TRADEDQTY":60},{"CLOSE":57500,"HIGH":57513,"LASTTRADETIME":1566464100000,"LOW":57450.05,"OPEN":57513,"OPENINTEREST":22790,"QUOTATIONLOT":10,"TRADEDQTY":30},{"CLOSE":57513,"HIGH":57599.85,"LASTTRADETIME":1566463800000,"LOW":57500,"OPEN":57599.85,"OPENINTEREST":22770,"QUOTATIONLOT":10,"TRADEDQTY":30},{"CLOSE":57599.85,"HIGH":57599.85,"LASTTRADETIME":1566463500000,"LOW":57500,"OPEN":57500,"OPENINTEREST":22770,"QUOTATIONLOT":10,"TRADEDQTY":20},{"CLOSE":57500,"HIGH":57500,"LASTTRADETIME":1566463200000,"LOW":57445.3,"OPEN":57499,"OPENINTEREST":22780,"QUOTATIONLOT":10,"TRADEDQTY":120},{"CLOSE":57499,"HIGH":57499.95,"LASTTRADETIME":1566462900000,"LOW":57435.95,"OPEN":57435.95,"OPENINTEREST":22810,"QUOTATIONLOT":10,"TRADEDQTY":30},{"CLOSE":57435.95,"HIGH":57500.15,"LASTTRADETIME":1566462600000,"LOW":57430,"OPEN":57450,"OPENINTEREST":22850,"QUOTATIONLOT":10,"TRADEDQTY":110},{"CLOSE":57450,"HIGH":57450,"LASTTRADETIME":1566462300000,"LOW":57380,"OPEN":57380,"OPENINTEREST":22840,"QUOTATIONLOT":10,"TRADEDQTY":300},{"CLOSE":57380,"HIGH":57380,"LASTTRADETIME":1566462000000,"LOW":57380,"OPEN":57380,"OPENINTEREST":22850,"QUOTATIONLOT":10,"TRADEDQTY":0},{"CLOSE":57380,"HIGH":57516.75,"LASTTRADETIME":1566461700000,"LOW":57377.15,"OPEN":57377.15,"OPENINTEREST":22850,"QUOTATIONLOT":10,"TRADEDQTY":110},{"CLOSE":57377.15,"HIGH":57377.15,"LASTTRADETIME":1566461400000,"LOW":57377.15,"OPEN":57377.15,"OPENINTEREST":22840,"QUOTATIONLOT":10,"TRADEDQTY":0},{"CLOSE":57377.15,"HIGH":57524.95,"LASTTRADETIME":1566461100000,"LOW":57377.15,"OPEN":57513.6,"OPENINTEREST":22840,"QUOTATIONLOT":10,"TRADEDQTY":80},{"CLOSE":57513.6,"HIGH":57564.55,"LASTTRADETIME":1566460800000,"LOW":57513.55,"OPEN":57540,"OPENINTEREST":22810,"QUOTATIONLOT":10,"TRADEDQTY":50},{"CLOSE":57484.35,"HIGH":57588,"LASTTRADETIME":1566460500000,"LOW":57484.35,"OPEN":57553.15,"OPENINTEREST":22800,"QUOTATIONLOT":10,"TRADEDQTY":70},{"CLOSE":57553.15,"HIGH":57553.15,"LASTTRADETIME":1566460200000,"LOW":57443.6,"OPEN":57443.6,"OPENINTEREST":22750,"QUOTATIONLOT":10,"TRADEDQTY":70},{"CLOSE":57443.6,"HIGH":57495,"LASTTRADETIME":1566459900000,"LOW":57443.6,"OPEN":57495,"OPENINTEREST":22720,"QUOTATIONLOT":10,"TRADEDQTY":10},{"CLOSE":57495,"HIGH":57500,"LASTTRADETIME":1566459600000,"LOW":57465.1,"OPEN":57493.75,"OPENINTEREST":22690,"QUOTATIONLOT":10,"TRADEDQTY":40},{"CLOSE":57493.75,"HIGH":57528.35,"LASTTRADETIME":1566459300000,"LOW":57426.45,"OPEN":57449.65,"OPENINTEREST":22690,"QUOTATIONLOT":10,"TRADEDQTY":90}],"meta":{"revision":0,"created":1566799803075,"version":0},"$loki":1}],"idIndex":[1],"binaryIndices":{},"constraints":null,"uniqueNames":["LASTTRADETIME"],"transforms":{},"objType":"5MINUTE","dirty":false,"cachedIndex":null,"cachedBinaryIndex":null,"cachedData":null,"adaptiveBinaryIndices":true,"transactional":false,"cloneObjects":false,"cloneMethod":"parse-stringify","asyncListeners":false,"disableMeta":false,"disableChangesApi":true,"disableDeltaChangesApi":true,"autoupdate":false,"serializableIndices":true,"ttl":null,"maxId":1,"DynamicViews":[],"events":{"insert":[],"update":[],"pre-insert":[],"pre-update":[],"close":[],"flushbuffer":[],"error":[],"delete":[null],"warning":[null]},"changes":[]}],"databaseVersion":1.5,"engineVersion":1.5,"autosave":true,"autosaveInterval":10000,"autosaveHandle":null,"throttledSaves":true,"options":{"autoload":true,"autosave":true,"unique":"name","autosaveInterval":10000,"serializationMethod":"normal","destructureDelimiter":"$<\n","recursiveWait":true,"recursiveWaitLimit":false,"recursiveWaitLimitDuration":2000,"started":1566799800012},"persistenceMethod":"fs","persistenceAdapter":null,"verbose":false,"events":{"init":[null],"loaded":[],"flushChanges":[],"close":[],"changes":[],"warning":[]},"ENV":"NODEJS"}