{"filename":"D:\\work\\IAMTRADER\\db\\stock\\MAITHANALL.json","collections":[{"name":"15MINUTE","data":[{"code":200,"status":"OK","timestamp":"2019-04-08T23:24:58+05:30","message":"historical-data","data":[{"timestamp":"1554435900000","open":"527","high":"529.65","low":"527","close":"527","volume":"2184"},{"timestamp":"1554436800000","open":"527","high":"528.35","low":"524.3","close":"526","volume":"834"},{"timestamp":"1554437700000","open":"526","high":"528.25","low":"525.15","close":"525.3","volume":"738"},{"timestamp":"1554438600000","open":"525.3","high":"528.25","low":"525.25","close":"525.55","volume":"1733"},{"timestamp":"1554439500000","open":"525.55","high":"525.8","low":"525.1","close":"525.1","volume":"145"},{"timestamp":"1554440400000","open":"525.1","high":"526","low":"524.3","close":"524.8","volume":"630"},{"timestamp":"1554441300000","open":"524.8","high":"524.8","low":"521","close":"521.75","volume":"1248"},{"timestamp":"1554442200000","open":"521.1","high":"522.1","low":"521.1","close":"521.3","volume":"71"},{"timestamp":"1554443100000","open":"521.3","high":"522","low":"521.1","close":"521.1","volume":"235"},{"timestamp":"1554444000000","open":"522.15","high":"523","low":"521.05","close":"523","volume":"369"},{"timestamp":"1554444900000","open":"523","high":"523","low":"521.1","close":"521.1","volume":"411"},{"timestamp":"1554445800000","open":"521.1","high":"522.05","low":"521.1","close":"522.05","volume":"320"},{"timestamp":"1554446700000","open":"522.05","high":"525.25","low":"522","close":"524.25","volume":"1483"},{"timestamp":"1554447600000","open":"524.25","high":"534.7","low":"522.1","close":"530.9","volume":"4443"},{"timestamp":"1554448500000","open":"530.75","high":"532.95","low":"527.3","close":"529.1","volume":"935"},{"timestamp":"1554449400000","open":"529.1","high":"532.95","low":"527.7","close":"531.8","volume":"823"},{"timestamp":"1554450300000","open":"530.55","high":"531.8","low":"530.55","close":"531.2","volume":"248"},{"timestamp":"1554451200000","open":"531.2","high":"531.7","low":"530.75","close":"530.9","volume":"86"},{"timestamp":"1554452100000","open":"530.9","high":"531.6","low":"528.05","close":"528.1","volume":"520"},{"timestamp":"1554453000000","open":"528.1","high":"530.9","low":"528.05","close":"530.85","volume":"1090"},{"timestamp":"1554453900000","open":"530.9","high":"530.9","low":"529","close":"530.25","volume":"50"},{"timestamp":"1554454800000","open":"530.25","high":"533","low":"530","close":"530.5","volume":"372"},{"timestamp":"1554455700000","open":"530.5","high":"531.5","low":"530.5","close":"531.5","volume":"211"},{"timestamp":"1554456600000","open":"531.5","high":"532","low":"530.25","close":"531.45","volume":"240"},{"timestamp":"1554457500000","open":"531.45","high":"534","low":"529.15","close":"531","volume":"2786"},{"timestamp":"1554695100000","open":"534.9","high":"536.3","low":"533.75","close":"534.05","volume":"925"},{"timestamp":"1554696000000","open":"534.05","high":"534.05","low":"531.15","close":"531.15","volume":"860"},{"timestamp":"1554696900000","open":"531.15","high":"532.95","low":"529.35","close":"531.75","volume":"1195"},{"timestamp":"1554697800000","open":"531.75","high":"531.95","low":"531","close":"531","volume":"317"},{"timestamp":"1554698700000","open":"531","high":"532.15","low":"529.85","close":"531.5","volume":"885"},{"timestamp":"1554699600000","open":"531.5","high":"532.75","low":"531","close":"532.05","volume":"534"},{"timestamp":"1554700500000","open":"532.05","high":"532.15","low":"531","close":"531.75","volume":"279"},{"timestamp":"1554701400000","open":"532.1","high":"532.75","low":"531.75","close":"532.5","volume":"230"},{"timestamp":"1554702300000","open":"532.5","high":"533.05","low":"532.05","close":"532.05","volume":"54"},{"timestamp":"1554703200000","open":"532.05","high":"534.25","low":"532.05","close":"534.2","volume":"182"},{"timestamp":"1554704100000","open":"534.2","high":"534.2","low":"533","close":"533.45","volume":"180"},{"timestamp":"1554705000000","open":"533.45","high":"533.6","low":"533","close":"533","volume":"378"},{"timestamp":"1554705900000","open":"533","high":"533.55","low":"533","close":"533.35","volume":"443"},{"timestamp":"1554706800000","open":"533.35","high":"533.95","low":"533","close":"533.4","volume":"221"},{"timestamp":"1554707700000","open":"533.4","high":"533.4","low":"533","close":"533.05","volume":"292"},{"timestamp":"1554708600000","open":"533.05","high":"533.05","low":"533.05","close":"533.05","volume":"2"},{"timestamp":"1554709500000","open":"533.05","high":"533.05","low":"531.1","close":"531.1","volume":"305"},{"timestamp":"1554710400000","open":"531.1","high":"531.55","low":"529.5","close":"530","volume":"955"},{"timestamp":"1554711300000","open":"530","high":"530.3","low":"527.45","close":"527.45","volume":"224"},{"timestamp":"1554712200000","open":"527.45","high":"527.45","low":"524.6","close":"525.1","volume":"794"},{"timestamp":"1554713100000","open":"525.1","high":"527.05","low":"525","close":"525","volume":"749"},{"timestamp":"1554714000000","open":"524.6","high":"524.6","low":"519.4","close":"521.15","volume":"3498"},{"timestamp":"1554714900000","open":"521.15","high":"525.55","low":"520","close":"523.95","volume":"353"},{"timestamp":"1554715800000","open":"523.95","high":"526","low":"523.95","close":"525","volume":"251"},{"timestamp":"1554716700000","open":"525","high":"526","low":"524.65","close":"526","volume":"1286"}],"meta":{"revision":0,"created":1554746107189,"version":0},"$loki":1}],"idIndex":[1],"binaryIndices":{},"constraints":null,"uniqueNames":[],"transforms":{},"objType":"15MINUTE","dirty":false,"cachedIndex":null,"cachedBinaryIndex":null,"cachedData":null,"adaptiveBinaryIndices":true,"transactional":false,"cloneObjects":false,"cloneMethod":"parse-stringify","asyncListeners":false,"disableMeta":false,"disableChangesApi":true,"disableDeltaChangesApi":true,"autoupdate":false,"serializableIndices":true,"ttl":null,"maxId":1,"DynamicViews":[],"events":{"insert":[],"update":[],"pre-insert":[],"pre-update":[],"close":[],"flushbuffer":[],"error":[],"delete":[null],"warning":[null]},"changes":[]}],"databaseVersion":1.5,"engineVersion":1.5,"autosave":true,"autosaveInterval":10000,"autosaveHandle":null,"throttledSaves":true,"options":{"autoload":true,"autosave":true,"autosaveInterval":10000,"serializationMethod":"normal","destructureDelimiter":"$<\n","recursiveWait":true,"recursiveWaitLimit":false,"recursiveWaitLimitDuration":2000,"started":1554746105467},"persistenceMethod":"fs","persistenceAdapter":null,"verbose":false,"events":{"init":[null],"loaded":[],"flushChanges":[],"close":[],"changes":[],"warning":[]},"ENV":"NODEJS"}