{"filename":"D:\\work\\IAMTRADER\\db\\stock\\MANINDS.json","collections":[{"name":"15MINUTE","data":[{"code":200,"status":"OK","timestamp":"2019-04-08T23:25:00+05:30","message":"historical-data","data":[{"timestamp":"1554435900000","open":"68.85","high":"69.4","low":"68.85","close":"69","volume":"1046"},{"timestamp":"1554436800000","open":"69","high":"69.4","low":"69","close":"69.2","volume":"958"},{"timestamp":"1554437700000","open":"69.2","high":"69.5","low":"69.15","close":"69.35","volume":"1086"},{"timestamp":"1554438600000","open":"69.15","high":"69.15","low":"69.1","close":"69.1","volume":"60"},{"timestamp":"1554439500000","open":"69.1","high":"69.3","low":"69","close":"69","volume":"1200"},{"timestamp":"1554440400000","open":"69","high":"69.25","low":"69","close":"69.25","volume":"1370"},{"timestamp":"1554441300000","open":"69.25","high":"69.25","low":"69.05","close":"69.05","volume":"62"},{"timestamp":"1554442200000","open":"69.05","high":"69.1","low":"69.05","close":"69.1","volume":"58"},{"timestamp":"1554443100000","open":"69.1","high":"69.5","low":"69","close":"69.5","volume":"3137"},{"timestamp":"1554444000000","open":"69.5","high":"69.8","low":"69.2","close":"69.2","volume":"3424"},{"timestamp":"1554444900000","open":"69.2","high":"69.35","low":"69.1","close":"69.1","volume":"111"},{"timestamp":"1554445800000","open":"69.1","high":"69.15","low":"69.1","close":"69.15","volume":"150"},{"timestamp":"1554446700000","open":"69.15","high":"69.45","low":"69.15","close":"69.35","volume":"575"},{"timestamp":"1554447600000","open":"69.35","high":"69.35","low":"69.35","close":"69.35","volume":"0"},{"timestamp":"1554448500000","open":"69.35","high":"69.45","low":"67.85","close":"68.55","volume":"15723"},{"timestamp":"1554449400000","open":"68.55","high":"68.55","low":"68.05","close":"68.1","volume":"111"},{"timestamp":"1554450300000","open":"68.1","high":"68.45","low":"68.1","close":"68.45","volume":"589"},{"timestamp":"1554451200000","open":"68.45","high":"68.5","low":"68.25","close":"68.45","volume":"433"},{"timestamp":"1554452100000","open":"68.45","high":"68.5","low":"68.45","close":"68.5","volume":"370"},{"timestamp":"1554453000000","open":"68.5","high":"68.5","low":"68.3","close":"68.3","volume":"6"},{"timestamp":"1554453900000","open":"68.3","high":"68.5","low":"68.3","close":"68.5","volume":"867"},{"timestamp":"1554454800000","open":"68.5","high":"68.6","low":"68.5","close":"68.5","volume":"800"},{"timestamp":"1554455700000","open":"68.5","high":"68.55","low":"68.2","close":"68.35","volume":"875"},{"timestamp":"1554456600000","open":"68.35","high":"68.4","low":"68.25","close":"68.3","volume":"332"},{"timestamp":"1554457500000","open":"68.3","high":"68.6","low":"68.2","close":"68.6","volume":"4164"},{"timestamp":"1554695100000","open":"69","high":"69","low":"68.2","close":"68.2","volume":"1141"},{"timestamp":"1554696000000","open":"68.2","high":"68.5","low":"68.15","close":"68.4","volume":"2940"},{"timestamp":"1554696900000","open":"68.4","high":"68.45","low":"68.15","close":"68.3","volume":"882"},{"timestamp":"1554697800000","open":"68.3","high":"68.5","low":"68.2","close":"68.5","volume":"597"},{"timestamp":"1554698700000","open":"68.5","high":"68.7","low":"68.5","close":"68.6","volume":"171"},{"timestamp":"1554699600000","open":"68.6","high":"68.6","low":"68.1","close":"68.1","volume":"11362"},{"timestamp":"1554700500000","open":"68.1","high":"68.1","low":"68.1","close":"68.1","volume":"0"},{"timestamp":"1554701400000","open":"68.3","high":"68.3","low":"68.1","close":"68.15","volume":"194"},{"timestamp":"1554702300000","open":"68.15","high":"68.15","low":"68.15","close":"68.15","volume":"0"},{"timestamp":"1554703200000","open":"68.15","high":"68.35","low":"68.15","close":"68.35","volume":"210"},{"timestamp":"1554704100000","open":"68.35","high":"69","low":"68.2","close":"68.25","volume":"4320"},{"timestamp":"1554705000000","open":"68.25","high":"68.45","low":"68.15","close":"68.15","volume":"1130"},{"timestamp":"1554705900000","open":"68.15","high":"68.4","low":"68.15","close":"68.4","volume":"202"},{"timestamp":"1554706800000","open":"68.4","high":"68.4","low":"68.4","close":"68.4","volume":"0"},{"timestamp":"1554707700000","open":"68.4","high":"68.4","low":"68.2","close":"68.2","volume":"300"},{"timestamp":"1554708600000","open":"68.2","high":"68.2","low":"68.15","close":"68.15","volume":"100"},{"timestamp":"1554709500000","open":"68.15","high":"68.15","low":"67.7","close":"68","volume":"2409"},{"timestamp":"1554710400000","open":"68","high":"68","low":"66.75","close":"67","volume":"15319"},{"timestamp":"1554711300000","open":"67","high":"67","low":"66.9","close":"67","volume":"4644"},{"timestamp":"1554712200000","open":"67","high":"67.7","low":"67","close":"67.7","volume":"2979"},{"timestamp":"1554713100000","open":"67.7","high":"67.75","low":"66.9","close":"67.05","volume":"3175"},{"timestamp":"1554714000000","open":"67.05","high":"67.55","low":"67.05","close":"67.55","volume":"2"},{"timestamp":"1554714900000","open":"67.55","high":"67.55","low":"67.25","close":"67.5","volume":"308"},{"timestamp":"1554715800000","open":"67.5","high":"67.5","low":"67.4","close":"67.4","volume":"138"},{"timestamp":"1554716700000","open":"67.4","high":"67.8","low":"67.2","close":"67.25","volume":"3000"}],"meta":{"revision":0,"created":1554746108294,"version":0},"$loki":1}],"idIndex":[1],"binaryIndices":{},"constraints":null,"uniqueNames":[],"transforms":{},"objType":"15MINUTE","dirty":false,"cachedIndex":null,"cachedBinaryIndex":null,"cachedData":null,"adaptiveBinaryIndices":true,"transactional":false,"cloneObjects":false,"cloneMethod":"parse-stringify","asyncListeners":false,"disableMeta":false,"disableChangesApi":true,"disableDeltaChangesApi":true,"autoupdate":false,"serializableIndices":true,"ttl":null,"maxId":1,"DynamicViews":[],"events":{"insert":[],"update":[],"pre-insert":[],"pre-update":[],"close":[],"flushbuffer":[],"error":[],"delete":[null],"warning":[null]},"changes":[]}],"databaseVersion":1.5,"engineVersion":1.5,"autosave":true,"autosaveInterval":10000,"autosaveHandle":null,"throttledSaves":true,"options":{"autoload":true,"autosave":true,"autosaveInterval":10000,"serializationMethod":"normal","destructureDelimiter":"$<\n","recursiveWait":true,"recursiveWaitLimit":false,"recursiveWaitLimitDuration":2000,"started":1554746107399},"persistenceMethod":"fs","persistenceAdapter":null,"verbose":false,"events":{"init":[null],"loaded":[],"flushChanges":[],"close":[],"changes":[],"warning":[]},"ENV":"NODEJS"}